[
    {
        "duration": 370.7333984375,
        "name": "sdk:sendFunnelTestCompleted",
        "startTime": 1771522309255.3008,
        "worker": "44204-29028",
        "status": true,
        "failure": null,
        "details": null,
        "entryType": "measure",
        "platform": "4",
        "command": null,
        "testName": null,
        "hookType": null,
        "cli": true
    },
    {
        "duration": 2708.230712890625,
        "name": "sdk:auto-capture",
        "startTime": 1771522309256.2998,
        "worker": "29816-29028",
        "status": true,
        "failure": null,
        "details": null,
        "entryType": "measure",
        "platform": "4",
        "command": null,
        "testName": null,
        "hookType": null,
        "cli": true
    },
    {
        "duration": 2732.419921875,
        "name": "sdk:exit-handler",
        "startTime": 1771522309251.1729,
        "worker": "7524-29028",
        "status": true,
        "failure": null,
        "details": null,
        "entryType": "measure",
        "platform": "4",
        "command": null,
        "testName": null,
        "hookType": null,
        "cli": true
    }
]